aredis_om/__init__.py
aredis_om/async_redis.py
aredis_om/checks.py
aredis_om/connections.py
aredis_om/py.typed
aredis_om/redisvl.py
aredis_om/settings.py
aredis_om/sync_redis.py
aredis_om/util.py
aredis_om/cli/__init__.py
aredis_om/cli/main.py
aredis_om/model/__init__.py
aredis_om/model/encoders.py
aredis_om/model/model.py
aredis_om/model/query_resolver.py
aredis_om/model/render_tree.py
aredis_om/model/token_escaper.py
aredis_om/model/types.py
aredis_om/model/cli/__init__.py
aredis_om/model/cli/index.py
aredis_om/model/cli/migrate.py
aredis_om/model/cli/migrate_data.py
aredis_om/model/migrations/__init__.py
aredis_om/model/migrations/data/__init__.py
aredis_om/model/migrations/data/base.py
aredis_om/model/migrations/data/migrator.py
aredis_om/model/migrations/data/builtin/__init__.py
aredis_om/model/migrations/data/builtin/datetime_migration.py
aredis_om/model/migrations/schema/__init__.py
aredis_om/model/migrations/schema/base.py
aredis_om/model/migrations/schema/legacy_migrator.py
aredis_om/model/migrations/schema/migrator.py
aredis_om/model/migrations/utils/__init__.py
redis_om/__init__.py
redis_om/async_redis.py
redis_om/checks.py
redis_om/connections.py
redis_om/redisvl.py
redis_om/settings.py
redis_om/sync_redis.py
redis_om/util.py
redis_om/cli/__init__.py
redis_om/cli/main.py
redis_om/model/__init__.py
redis_om/model/encoders.py
redis_om/model/model.py
redis_om/model/query_resolver.py
redis_om/model/render_tree.py
redis_om/model/token_escaper.py
redis_om/model/types.py
redis_om/model/cli/__init__.py
redis_om/model/cli/index.py
redis_om/model/cli/migrate.py
redis_om/model/cli/migrate_data.py
redis_om/model/migrations/__init__.py
redis_om/model/migrations/data/__init__.py
redis_om/model/migrations/data/base.py
redis_om/model/migrations/data/migrator.py
redis_om/model/migrations/data/builtin/__init__.py
redis_om/model/migrations/data/builtin/datetime_migration.py
redis_om/model/migrations/schema/__init__.py
redis_om/model/migrations/schema/base.py
redis_om-1.0.6.dist-info/METADATA
redis_om-1.0.6.dist-info/WHEEL
redis_om-1.0.6.dist-info/entry_points.txt
redis_om-1.0.6.dist-info/licenses/LICENSE
redis_om-1.0.6.dist-info/RECORD
