Metadata-Version: 2.4
Name: redis-om
Version: 1.0.6
Summary: Object mappings, and more, for Redis.
Project-URL: Repository, https://github.com/redis/redis-om-python
Project-URL: Code, https://github.com/redis/redis-om-python
Project-URL: Issue tracker, https://github.com/redis/redis-om-python/issues
Author-email: Redis OSS <oss@redis.com>
Maintainer-email: Redis OSS <oss@redis.com>
License: BSD-3-Clause
License-File: LICENSE
Classifier: Development Status :: 5 - Production/Stable
Classifier: Environment :: Console
Classifier: Intended Audience :: Developers
Classifier: License :: OSI Approved :: BSD License
Classifier: Operating System :: OS Independent
Classifier: Programming Language :: Python
Classifier: Programming Language :: Python :: 3.10
Classifier: Programming Language :: Python :: 3.11
Classifier: Programming Language :: Python :: 3.12
Classifier: Programming Language :: Python :: 3.13
Classifier: Topic :: Database
Requires-Python: <4.0,>=3.10
Requires-Dist: click>=8.0.1
Requires-Dist: hiredis<4.0.0,>=2.2.3
Requires-Dist: more-itertools<11.0,>=8.14
Requires-Dist: pydantic-extra-types>=2.10.5
Requires-Dist: pydantic<3.0.0,>=2.0.0
Requires-Dist: python-ulid<=3.1.0,>=1.0.3
Requires-Dist: redis<8.0.0,>=4.2.0
Requires-Dist: redisvl>=0.13.0
Requires-Dist: setuptools>=70.0
Requires-Dist: types-redis<5.0.0,>=3.5.9
Requires-Dist: typing-extensions>=4.4.0
Provides-Extra: examples
Requires-Dist: asgi-lifespan>=2.1.0; extra == 'examples'
Requires-Dist: fastapi>=0.128.0; extra == 'examples'
Requires-Dist: flask>=3.1.2; extra == 'examples'
Requires-Dist: httpx>=0.28.1; extra == 'examples'
Requires-Dist: uvicorn>=0.40.0; extra == 'examples'
